LICENSE
c64os_util/__init__.py
c64os_util/car/__init__.py
c64os_util/car/archive.py
c64os_util/car/common.py
c64os_util/car/header.py
c64os_util/car/record/__init__.py
c64os_util/car/record/header.py
c64os_util/car/record/record.py
c64os_util/util/__init__.py
c64os_util/util/codec.py
c64os_util/util/functions.py
c64os_util-0.0.1.dist-info/LICENSE
c64os_util-0.0.1.dist-info/METADATA
c64os_util-0.0.1.dist-info/WHEEL
c64os_util-0.0.1.dist-info/entry_points.txt
c64os_util-0.0.1.dist-info/RECORD
