Metadata-Version: 2.1
Name: c64os-util
Version: 0.0.1
Summary: A collection of utilities for dealing with C64 OS files.
Home-page: https://pypi.org/p/c64os-util
License: MIT
Keywords: commodore,c64,C64 OS
Author: voidstar
Author-email: voidstar@anachronauts.club
Requires-Python: >=3.10,<4.0
Classifier: Environment :: Console
Classifier: License :: OSI Approved :: MIT License
Classifier: Operating System :: OS Independent
Classifier: Programming Language :: Python :: 3
Classifier: Programming Language :: Python :: 3.10
Classifier: Programming Language :: Python :: 3.11
Classifier: Topic :: Software Development :: Libraries :: Python Modules
Project-URL: Documentation, https://c64os-util.readthedocs.io/
Project-URL: Repository, https://github.com/woodrowbarlow/c64os-util
